PyAnimator/__init__.py
PyAnimator-0.5.dist-info/METADATA
PyAnimator-0.5.dist-info/WHEEL
PyAnimator-0.5.dist-info/top_level.txt
PyAnimator-0.5.dist-info/RECORD
