Metadata-Version: 2.1
Name: PyAnimator
Version: 0.5
Summary: Create awesome animation's with only one line of code !
Home-page: https://github.com/AzgarDev/animator
Author: AzgarD
Author-email: anon@gmail.com
License: MIT
Download-URL: https://github.com/AzgarDev/animator/archive/v_0.3.tar.gz
Keywords: Animation,RGB animation python,Python rgb animation
Platform: UNKNOWN
Classifier: Development Status :: 3 - Alpha
Classifier: Intended Audience :: Developers
Classifier: Topic :: Software Development :: Build Tools
Classifier: License :: OSI Approved :: MIT License
Classifier: Programming Language :: Python :: 3
Classifier: Programming Language :: Python :: 3.4
Classifier: Programming Language :: Python :: 3.5
Classifier: Programming Language :: Python :: 3.6
Classifier: Programming Language :: Python :: 3.7
Classifier: Programming Language :: Python :: 3.8
Classifier: Programming Language :: Python :: 3.9
Requires-Dist: colorama
